klunsimplemodule/__init__.py
klunsimplemodule/add.py
klunsimplemodule/substract.py
klunsimplemodule/extras/__init__.py
klunsimplemodule/extras/divide.py
klunsimplemodule/extras/multiply.py
simple_module/__init__.py
simple_module/add.py
simple_module/substract.py
simple_module/extras/__init__.py
simple_module/extras/divide.py
simple_module/extras/multiply.py
klunsimplemodule-0.0.4.dist-info/METADATA
klunsimplemodule-0.0.4.dist-info/WHEEL
klunsimplemodule-0.0.4.dist-info/top_level.txt
klunsimplemodule-0.0.4.dist-info/RECORD
