Metadata-Version: 2.1
Name: klunsimplemodule
Version: 0.0.4
Summary: My first Python package
Home-page: UNKNOWN
Author: k lun
Author-email: <youremail@email.com>
License: UNKNOWN
Keywords: python,my first package
Platform: UNKNOWN
Classifier: Development Status :: 3 - Alpha
Classifier: Intended Audience :: Education
Classifier: Programming Language :: Python :: 2
Classifier: Programming Language :: Python :: 3
Classifier: Operating System :: MacOS :: MacOS X
Classifier: Operating System :: Microsoft :: Windows
